README.md
setup.cfg
setup.py
metis_python.egg-info/PKG-INFO
metis_python.egg-info/SOURCES.txt
metis_python.egg-info/dependency_links.txt
metis_python.egg-info/not-zip-safe
metis_python.egg-info/requires.txt
metis_python.egg-info/top_level.txt
metispy/__init__.py
metispy/metis.py