Metadata-Version: 1.1
Name: metis-python
Version: 0.1
Summary: Wrapper for metis to support lastest networkx.
Home-page: https://github.com/james77777778/python_metis
Author: Hong-Yu Chiu
Author-email: james77777778@gmail.com
License: MIT
Keywords: metis,graph,partition
Platform: UNKNOWN
Classifier: Development Status :: 5 - Production/Stable
Classifier: License :: OSI Approved :: MIT License
Classifier: Programming Language :: Python :: 3.5
Classifier: Programming Language :: Python :: 3.6
